rig_core/__init__.py
rig_core/all.py
rig_core/contextmanager.py
rig_core/ctx.py
rig_core/db.py
rig_core/filter.py
rig_core/joint_tree.py
rig_core/response.py
rig_core/tag.py
maya_rig_core-0.2.5.dist-info/LICENSE
maya_rig_core-0.2.5.dist-info/METADATA
maya_rig_core-0.2.5.dist-info/WHEEL
maya_rig_core-0.2.5.dist-info/top_level.txt
maya_rig_core-0.2.5.dist-info/RECORD
